{
    "type": "root",
    "children": [
        {
            "type": "section",
            "data": {
                "name": "plant-uml",
                "hName": "section",
                "hProperties": {
                    "depth": 1
                }
            },
            "depth": 1,
            "children": [
                {
                    "type": "cell",
                    "position": {
                        "start": {
                            "line": 1,
                            "column": 1,
                            "offset": 0
                        },
                        "end": {
                            "line": 1,
                            "column": 14,
                            "offset": 13
                        }
                    },
                    "data": {
                        "hName": "cell",
                        "hProperties": {
                            "class": "cell"
                        },
                        "section": {
                            "position": {
                                "start": {
                                    "line": 1,
                                    "column": 1,
                                    "offset": 0
                                },
                                "end": {
                                    "line": 5,
                                    "column": 4,
                                    "offset": 46
                                }
                            }
                        }
                    },
                    "children": [
                        {
                            "type": "heading",
                            "depth": 1,
                            "children": [
                                {
                                    "type": "text",
                                    "value": "Plant ",
                                    "position": {
                                        "start": {
                                            "line": 1,
                                            "column": 3,
                                            "offset": 2
                                        },
                                        "end": {
                                            "line": 1,
                                            "column": 9,
                                            "offset": 8
                                        }
                                    }
                                },
                                {
                                    "type": "inlineCode",
                                    "value": "uml",
                                    "position": {
                                        "start": {
                                            "line": 1,
                                            "column": 9,
                                            "offset": 8
                                        },
                                        "end": {
                                            "line": 1,
                                            "column": 14,
                                            "offset": 13
                                        }
                                    }
                                }
                            ],
                            "position": {
                                "start": {
                                    "line": 1,
                                    "column": 1,
                                    "offset": 0
                                },
                                "end": {
                                    "line": 1,
                                    "column": 14,
                                    "offset": 13
                                }
                            },
                            "data": {
                                "hProperties": {
                                    "id": "plant-uml"
                                },
                                "id": "plant-uml"
                            },
                            "processed": true
                        }
                    ]
                },
                {
                    "type": "cell",
                    "position": {
                        "start": {
                            "line": 3,
                            "column": 1,
                            "offset": 15
                        },
                        "end": {
                            "line": 5,
                            "column": 4,
                            "offset": 46
                        }
                    },
                    "data": {
                        "hName": "cell",
                        "hProperties": {
                            "class": "cell"
                        }
                    },
                    "children": [
                        {
                            "type": "code",
                            "lang": "uml",
                            "meta": "!below",
                            "value": "class Diagram",
                            "position": {
                                "start": {
                                    "line": 3,
                                    "column": 1,
                                    "offset": 15
                                },
                                "end": {
                                    "line": 5,
                                    "column": 4,
                                    "offset": 46
                                }
                            },
                            "data": {
                                "meta": {
                                    "attrs": {},
                                    "lang": "uml",
                                    "directives": [
                                        "below"
                                    ],
                                    "isOutput": false,
                                    "hasOutput": false,
                                    "hasSource": false,
                                    "raw": "uml !below"
                                },
                                "hProperties": {
                                    "className": "",
                                    "meta": {
                                        "attrs": {},
                                        "lang": "uml",
                                        "directives": [
                                            "below"
                                        ],
                                        "isOutput": false,
                                        "hasOutput": false,
                                        "hasSource": false,
                                        "raw": "uml !below"
                                    }
                                }
                            }
                        }
                    ]
                }
            ],
            "position": {
                "start": {
                    "line": 1,
                    "column": 1,
                    "offset": 0
                },
                "end": {
                    "line": 5,
                    "column": 4,
                    "offset": 46
                }
            }
        }
    ],
    "position": {
        "start": {
            "line": 1,
            "column": 1,
            "offset": 0
        },
        "end": {
            "line": 5,
            "column": 4,
            "offset": 46
        }
    }
}